{"color": "#004834", "hometowns": {"Hutto, TX": {"count": 1, "lat": "30.5427638", "lon": "-97.5468898"}, "Mesquite, TX": {"count": 2, "lat": "32.7666103", "lon": "-96.599472"}, "Dallas, TX": {"count": 2, "lat": "32.7762719", "lon": "-96.7968558"}, "Richmond, TX": {"count": 1, "lat": "29.5821811", "lon": "-95.7607832"}, "Las Vegas, NV": {"count": 1, "lat": "36.1662859", "lon": "-115.149225"}, "Copperas Cove, TX": {"count": 1, "lat": "31.124062", "lon": "-97.9030785"}, "Richardson, TX": {"count": 1, "lat": "32.9481789", "lon": "-96.7297206"}, "Pflugerville, TX": {"count": 1, "lat": "30.4393696", "lon": "-97.6200043"}, "Huntersville, NC": {"count": 1, "lat": "35.4107135", "lon": "-80.8428483"}, "Shreveport, LA": {"count": 2, "lat": "32.4828485", "lon": "-93.8284831615932"}, "The Woodlands, TX": {"count": 1, "lat": "30.1734194", "lon": "-95.504686"}, "Trinidad, CO": {"count": 1, "lat": "37.169397", "lon": "-104.5005411"}, "Rockwall, TX": {"count": 2, "lat": "32.9312336", "lon": "-96.4597089"}, "Lancaster, TX": {"count": 1, "lat": "32.5920798", "lon": "-96.7561083"}, "Lake Forest, CA": {"count": 1, "lat": "33.6469661", "lon": "-117.689218"}, "Tyler, TX": {"count": 1, "lat": "32.3512601", "lon": "-95.3010624"}, "Kingwood, TX": {"count": 1, "lat": "30.0335526", "lon": "-95.2610444"}, "Rockdale, TX": {"count": 1, "lat": "30.6554759", "lon": "-97.0013744"}, "Wylie, TX": {"count": 3, "lat": "33.0151201", "lon": "-96.5388789"}, "Port Arthur, TX": {"count": 1, "lat": "29.8988258", "lon": "-93.9287815"}, "Waxahachie, TX": {"count": 1, "lat": "32.3884555", "lon": "-96.92882370837"}, "Arlington, TX": {"count": 2, "lat": "32.7355816", "lon": "-97.1071186"}, "Australia": {"count": 2, "lat": "-24.7761085", "lon": "134.755"}, "Lorena, TX": {"count": 1, "lat": "31.3865592", "lon": "-97.2155596"}, "Willis, TX": {"count": 1, "lat": "30.4249276", "lon": "-95.4799418"}, "Irving, TX": {"count": 2, "lat": "32.8629195", "lon": "-96.9791701654883"}, "Refugio, TX": {"count": 1, "lat": "28.3045305", "lon": "-97.2745885"}, "Amarillo, TX": {"count": 2, "lat": "35.2072185", "lon": "-101.8338246"}, "Bryan, TX": {"count": 1, "lat": "30.693444", "lon": "-96.4008017154952"}, "Sugar Land, TX": {"count": 1, "lat": "29.6196787", "lon": "-95.6349463"}, "Texarkana, TX": {"count": 1, "lat": "33.425125", "lon": "-94.0476882"}, "Lansdowne, PA": {"count": 1, "lat": "39.9381682", "lon": "-75.2718507"}, "Little River, TX": {"count": 1, "lat": "30.8343357", "lon": "-96.9487135"}, "Cedar Park, TX": {"count": 1, "lat": "30.4650543", "lon": "-97.8126677028017"}, "Euless, TX": {"count": 2, "lat": "32.83726", "lon": "-97.0997889"}, "Scottsdale, AZ": {"count": 1, "lat": "33.5091215", "lon": "-111.8992365"}, "Missouri City, TX": {"count": 2, "lat": "29.6330685", "lon": "-95.5375481980769"}, "Waco, TX": {"count": 9, "lat": "31.549333", "lon": "-97.1466695"}, "Killeen, TX": {"count": 1, "lat": "31.1171441", "lon": "-97.727796"}, "Linden, TX": {"count": 1, "lat": "33.0123537", "lon": "-94.3654707"}, "Magnolia, TX": {"count": 1, "lat": "30.2093794", "lon": "-95.7507815"}, "Austin, TX": {"count": 1, "lat": "30.2711286", "lon": "-97.7436994"}, "Mart, TX": {"count": 1, "lat": "31.5423911", "lon": "-96.8336015"}, "Navasota, TX": {"count": 1, "lat": "30.3874135", "lon": "-96.0875066"}, "Frisco, TX": {"count": 1, "lat": "33.1506744", "lon": "-96.8236116"}, "Desoto, TX": {"count": 1, "lat": "29.390781", "lon": "-98.5267979"}, "Gilmer, TX": {"count": 1, "lat": "32.7287472", "lon": "-94.9424379"}, "Sherman, TX": {"count": 1, "lat": "33.617501", "lon": "-96.5954934338983"}, "Booker, TX": {"count": 1, "lat": "36.4533648", "lon": "-100.5373673"}, "SAN ANTONIO, TX": {"count": 1, "lat": "29.4246002", "lon": "-98.4951405"}, "Garland, TX": {"count": 1, "lat": "32.912624", "lon": "-96.6388833"}, "Park City, UT": {"count": 1, "lat": "40.6460635", "lon": "-111.4979741"}, "Burkburnett, TX": {"count": 1, "lat": "34.0978711", "lon": "-98.5706134"}, "Gatesville, TX": {"count": 2, "lat": "31.4351645", "lon": "-97.743911"}, "Ennis, TX": {"count": 1, "lat": "32.3293111", "lon": "-96.6252679"}, "Sherman Oaks, CA": {"count": 1, "lat": "34.1508718", "lon": "-118.4489865"}, "Princeton, TX": {"count": 1, "lat": "33.1801161", "lon": "-96.4980424"}, "Paris, TX": {"count": 1, "lat": "33.6617962", "lon": "-95.555513"}, "Stephenville, TX": {"count": 2, "lat": "32.2207307", "lon": "-98.2026165"}, "Plano, TX": {"count": 1, "lat": "33.0136764", "lon": "-96.6925096"}, "Carlsbad, CA": {"count": 1, "lat": "33.1580933", "lon": "-117.3505939"}, "Katy, TX": {"count": 1, "lat": "29.7857853", "lon": "-95.8243956"}, "Ringling, OK": {"count": 1, "lat": "34.1784265", "lon": "-97.5925265"}, "Kilgore, TX": {"count": 1, "lat": "32.3860733", "lon": "-94.8758462"}, "Pearland, TX": {"count": 1, "lat": "29.5639758", "lon": "-95.2864299"}, "Orange, TX": {"count": 1, "lat": "30.1228634", "lon": "-93.9041169"}, "Gaithersburg, MD": {"count": 1, "lat": "39.1434406", "lon": "-77.2013705"}, "Nacogdoches, TX": {"count": 1, "lat": "31.5970503", "lon": "-94.5927451"}, "Mount Pleasant, TX": {"count": 1, "lat": "33.1567863", "lon": "-94.968269"}, "Longview, TX": {"count": 1, "lat": "32.5007038", "lon": "-94.7404891"}, "Mckinney, TX": {"count": 3, "lat": "33.1976496", "lon": "-96.6154471"}, "Grand Prairie, TX": {"count": 1, "lat": "32.7459645", "lon": "-96.9977846"}, "Bakersfield, CA": {"count": 1, "lat": "35.3738712", "lon": "-119.0194639"}, "Everman, TX": {"count": 1, "lat": "32.630968", "lon": "-97.2891817"}, "Odessa, TX": {"count": 1, "lat": "31.8457149", "lon": "-102.367687"}, "Cibolo, TX": {"count": 1, "lat": "29.561618", "lon": "-98.2269553"}, "Rowlett, TX": {"count": 1, "lat": "32.9029017", "lon": "-96.56388"}, "Cypress, TX": {"count": 2, "lat": "29.9691116", "lon": "-95.6971685"}, "Jenison, MI": {"count": 1, "lat": "42.9072481", "lon": "-85.7919784"}, "Arp, TX": {"count": 1, "lat": "32.2254332", "lon": "-95.0577207"}, "Abilene, TX": {"count": 2, "lat": "32.4464534", "lon": "-99.7333478"}, "Aurora, IL": {"count": 1, "lat": "41.7605849", "lon": "-88.3200715"}, "Houston, TX": {"count": 8, "lat": "29.7589382", "lon": "-95.3676973"}, "Pacifica, CA": {"count": 1, "lat": "37.6138253", "lon": "-122.4869194"}, "Allen, TX": {"count": 2, "lat": "33.1031744", "lon": "-96.6705503"}}, "name": "Baylor", "license": "Data \u00a9 OpenStreetMap contributors, ODbL 1.0. http://www.openstreetmap.org/copyright"}