{"color": "#d1c57e", "hometowns": {"Snellville, GA": {"count": 1, "lat": "33.857328", "lon": "-84.0199108"}, "Dallas, TX": {"count": 1, "lat": "32.7762719", "lon": "-96.7968558"}, "Palos Verdes, CA": {"count": 1, "lat": "33.7483311", "lon": "-118.3707683"}, "Colorado Springs, CO": {"count": 1, "lat": "38.8339578", "lon": "-104.8253485"}, "Arvada, CO": {"count": 1, "lat": "39.8027644", "lon": "-105.0874842"}, "Chandler, AZ": {"count": 1, "lat": "33.3067132", "lon": "-111.8408489"}, "Compton, CA": {"count": 1, "lat": "33.8941926", "lon": "-118.2254756"}, "Altadena, CA": {"count": 1, "lat": "34.1863161", "lon": "-118.1352329"}, "El Paso, TX": {"count": 2, "lat": "31.8111305", "lon": "-106.501349295577"}, "Laplace, LA": {"count": 1, "lat": "52.0977181", "lon": "19.0258159"}, "Valencia, CA": {"count": 1, "lat": "10.1704877", "lon": "-68.0011214"}, "Oceanside, CA": {"count": 1, "lat": "33.1958696", "lon": "-117.3794834"}, "Ontario, CA": {"count": 1, "lat": "50.0000002", "lon": "-86.0000001"}, "Thousand Oaks, CA": {"count": 3, "lat": "34.17142715", "lon": "-118.910587629744"}, "Clifton Park, NY": {"count": 1, "lat": "42.8656325", "lon": "-73.7709535"}, "Aiken, SC": {"count": 1, "lat": "33.5598586", "lon": "-81.721952"}, "Centennial, CO": {"count": 2, "lat": "39.5680644", "lon": "-104.97783071285"}, "West Hills, CA": {"count": 1, "lat": "34.1340752", "lon": "-118.3215862"}, "Gulfport, MS": {"count": 1, "lat": "30.3674198", "lon": "-89.0928155"}, "Highlands Ranch, CO": {"count": 3, "lat": "39.5538771", "lon": "-104.9694264"}, "Longmont, CO": {"count": 1, "lat": "40.1672117", "lon": "-105.1019287"}, "Van Nuys, CA": {"count": 1, "lat": "34.1866581", "lon": "-118.448729"}, "La Mirada, CA": {"count": 1, "lat": "33.9060971", "lon": "-118.0107092"}, "The Woodlands, TX": {"count": 2, "lat": "30.1734194", "lon": "-95.504686"}, "Burlingame, CA": {"count": 1, "lat": "37.5841026", "lon": "-122.3660825"}, "Sacramento, CA": {"count": 3, "lat": "38.5815719", "lon": "-121.4943995"}, "Northridge, CA": {"count": 1, "lat": "34.2285918", "lon": "-118.5369316"}, "Los Altos, CA": {"count": 1, "lat": "37.3790629", "lon": "-122.116578"}, "Bellflower, CA": {"count": 1, "lat": "33.8825705", "lon": "-118.1167679"}, "San Jose, CA": {"count": 4, "lat": "37.3361905", "lon": "-121.8905833"}, "Parker, CO": {"count": 4, "lat": "39.5184514", "lon": "-104.7612638"}, "Temecula, CA": {"count": 1, "lat": "33.4946353", "lon": "-117.1473661"}, "Atherton, CA": {"count": 1, "lat": "37.4613272", "lon": "-122.197743"}, "Washington, DC": {"count": 3, "lat": "38.8949549", "lon": "-77.0366456"}, "Castle Rock, CO": {"count": 1, "lat": "39.3726585", "lon": "-104.8584264"}, "Eagle, ID": {"count": 1, "lat": "43.6954424", "lon": "-116.3540138"}, "Scottsdale, AZ": {"count": 1, "lat": "33.5091215", "lon": "-111.8992365"}, "Monrovia, CA": {"count": 1, "lat": "34.1483499", "lon": "-118.0014517"}, "Phoenix, AZ": {"count": 1, "lat": "33.4467681", "lon": "-112.0756724"}, "Rifle, CO": {"count": 1, "lat": "39.5347023", "lon": "-107.7831199"}, "Pomona, CA": {"count": 1, "lat": "34.0552886", "lon": "-117.7522793"}, "Kapolei, HI": {"count": 1, "lat": "21.3339504", "lon": "-158.0771853"}, "Saratoga, CA": {"count": 1, "lat": "37.2638324", "lon": "-122.0230146"}, "Palo Cedro, CA": {"count": 1, "lat": "40.548524", "lon": "-122.23278773213"}, "Boulder, CO": {"count": 2, "lat": "40.0149856", "lon": "-105.2705456"}, "Peoria, AZ": {"count": 1, "lat": "33.5766205", "lon": "-112.2398262"}, "Westlake Village, CA": {"count": 1, "lat": "34.1458389", "lon": "-118.8056474"}, "Goodyear, AZ": {"count": 1, "lat": "33.4001695", "lon": "-112.45722341601"}, "Tacoma, WA": {"count": 1, "lat": "47.2495798", "lon": "-122.4398746"}, "SAN ANTONIO, TX": {"count": 1, "lat": "29.4246002", "lon": "-98.4951405"}, "Park City, UT": {"count": 1, "lat": "40.6460635", "lon": "-111.4979741"}, "Sandy, UT": {"count": 1, "lat": "40.572851", "lon": "-111.833449531627"}, "Monument, CO": {"count": 1, "lat": "39.0916586", "lon": "-104.872758"}, "Westminster, CO": {"count": 1, "lat": "39.85541775", "lon": "-105.041568764084"}, "Templeton, CA": {"count": 1, "lat": "49.1966723", "lon": "-123.1464081"}, "Fort Collins, CO": {"count": 1, "lat": "40.5508527", "lon": "-105.0668085"}, "Riverside, CA": {"count": 1, "lat": "33.9533546", "lon": "-117.3961623"}, "Gilroy, CA": {"count": 1, "lat": "37.0065078", "lon": "-121.5631723"}, "Lone Tree, CO": {"count": 1, "lat": "39.5366435", "lon": "-104.885520850814"}, "Sylmar, CA": {"count": 1, "lat": "34.3076252", "lon": "-118.4492148"}, "Spring Valley, NY": {"count": 1, "lat": "41.1130231", "lon": "-74.0437839"}, "Covina, CA": {"count": 1, "lat": "34.0877926", "lon": "-117.8891164"}, "Englewood, CO": {"count": 1, "lat": "39.6482059", "lon": "-104.9879641"}, "San Luis Obispo, CA": {"count": 1, "lat": "35.2827525", "lon": "-120.6596156"}, "Mckees Rocks, PA": {"count": 1, "lat": "40.4656244", "lon": "-80.0656106"}, "Aurora, CO": {"count": 5, "lat": "39.729432", "lon": "-104.8319196"}, "Denver, CO": {"count": 3, "lat": "39.7391536", "lon": "-104.9847033"}, "Mexico": {"count": 1, "lat": "19.4325301", "lon": "-99.1332101"}, "Roseville, CA": {"count": 1, "lat": "38.72338", "lon": "-121.185878161131"}, "College Station, TX": {"count": 1, "lat": "30.6262616", "lon": "-96.3347249"}, "San Diego, CA": {"count": 3, "lat": "32.7174209", "lon": "-117.1627714"}, "Sierra Madre, CA": {"count": 1, "lat": "34.1616729", "lon": "-118.0528456"}, "Camarillo, CA": {"count": 1, "lat": "34.2163939", "lon": "-119.0376024"}, "Littleton, CO": {"count": 3, "lat": "39.613321", "lon": "-105.0166498"}, "Canyon Country, CA": {"count": 1, "lat": "34.4233293", "lon": "-118.4720281"}, "Mission Viejo, CA": {"count": 2, "lat": "33.5965685", "lon": "-117.659405"}, "Waianae, HI": {"count": 1, "lat": "21.4454875", "lon": "-158.187823787263"}, "Foothill Ranch, CA": {"count": 1, "lat": "33.6837644", "lon": "-117.6622499"}, "Cypress, TX": {"count": 2, "lat": "29.9691116", "lon": "-95.6971685"}, "Chula Vista, CA": {"count": 1, "lat": "32.6400541", "lon": "-117.0841955"}, "Granite Bay, CA": {"count": 1, "lat": "38.762173", "lon": "-121.185033445684"}, "Upland, CA": {"count": 2, "lat": "34.09751", "lon": "-117.6483876"}, "Houston, TX": {"count": 1, "lat": "29.7589382", "lon": "-95.3676973"}, "Decatur, GA": {"count": 1, "lat": "33.7737582", "lon": "-84.296069"}}, "name": "Colorado", "license": "Data \u00a9 OpenStreetMap contributors, ODbL 1.0. http://www.openstreetmap.org/copyright"}