{"color": "#00331b", "hometowns": {"Carrollton, TX": {"count": 1, "lat": "32.9537349", "lon": "-96.8902816"}, "Fort Wayne, IN": {"count": 2, "lat": "41.0799898", "lon": "-85.1386015"}, "Westlake, OH": {"count": 2, "lat": "41.4553232", "lon": "-81.9179174"}, "South Bend, IN": {"count": 1, "lat": "41.6833813", "lon": "-86.2500066"}, "Boynton Beach, FL": {"count": 1, "lat": "26.5253491", "lon": "-80.0664309"}, "Fair Lawn, NJ": {"count": 1, "lat": "40.9403762", "lon": "-74.1318096"}, "Lagrange, OH": {"count": 1, "lat": "41.2372753", "lon": "-82.119872"}, "Parker, CO": {"count": 1, "lat": "39.5184514", "lon": "-104.7612638"}, "Ottawa, IL": {"count": 1, "lat": "45.4210328", "lon": "-75.6900219"}, "Rochester, NY": {"count": 1, "lat": "43.1854754", "lon": "-77.6106860508176"}, "Auburn Hills, MI": {"count": 1, "lat": "42.6647495", "lon": "-83.230937513002"}, "Harper Woods, MI": {"count": 1, "lat": "42.4330924", "lon": "-82.9240833"}, "Paw Paw, MI": {"count": 1, "lat": "42.2178171", "lon": "-85.8911246"}, "Menomonee Falls, WI": {"count": 1, "lat": "43.1789322", "lon": "-88.1167148"}, "South Lyon, MI": {"count": 1, "lat": "42.451377", "lon": "-83.659179"}, "Elkhorn, WI": {"count": 1, "lat": "42.6727927", "lon": "-88.5445447"}, "Pickerington, OH": {"count": 1, "lat": "39.8842304", "lon": "-82.7535049"}, "Macomb, MI": {"count": 1, "lat": "42.6741189", "lon": "-82.902901"}, "Palmyra, VA": {"count": 1, "lat": "37.8609747", "lon": "-78.2633373"}, "Dewitt, MI": {"count": 1, "lat": "42.842382", "lon": "-84.5694103"}, "Maple Heights, OH": {"count": 1, "lat": "41.4153313", "lon": "-81.565956"}, "Ypsilanti, MI": {"count": 1, "lat": "42.2411499", "lon": "-83.6129939"}, "Temperance, MI": {"count": 2, "lat": "41.7793487", "lon": "-83.5688386"}, "Iowa City, IA": {"count": 1, "lat": "41.6612561", "lon": "-91.5299106"}, "Baxter, IA": {"count": 1, "lat": "41.8260998", "lon": "-93.1515905"}, "Kettering, OH": {"count": 1, "lat": "39.6895036", "lon": "-84.1688274"}, "Poseyville, IN": {"count": 1, "lat": "38.1700444", "lon": "-87.7830825"}, "New Port Richey, FL": {"count": 1, "lat": "28.2471345", "lon": "-82.717023717713"}, "Batavia, IL": {"count": 1, "lat": "48.5740136", "lon": "13.4606445"}, "Osseo, MN": {"count": 1, "lat": "45.1194091", "lon": "-93.4024532"}, "Lambertville, MI": {"count": 2, "lat": "41.7658819", "lon": "-83.6279921"}, "Elkton, MD": {"count": 1, "lat": "39.6067789", "lon": "-75.8332718"}, "Woodhaven, MI": {"count": 1, "lat": "42.1370519", "lon": "-83.2451066"}, "Jackson, MI": {"count": 2, "lat": "32.4104385", "lon": "-90.162064888255"}, "Colleyville, TX": {"count": 1, "lat": "32.8809603", "lon": "-97.155012"}, "Crozier, VA": {"count": 1, "lat": "37.6370639", "lon": "-77.7971297"}, "Brighton, MI": {"count": 1, "lat": "42.5316757", "lon": "-83.7844489"}, "Fruitport, MI": {"count": 2, "lat": "43.1306702", "lon": "-86.1546822"}, "Coldwater, OH": {"count": 1, "lat": "40.4797688", "lon": "-84.628291"}, "Akron, OH": {"count": 1, "lat": "41.0830643", "lon": "-81.5184854"}, "Norwalk, OH": {"count": 1, "lat": "41.2425531", "lon": "-82.6157331"}, "Detroit, MI": {"count": 3, "lat": "42.3486635", "lon": "-83.0567375"}, "Gilbert, AZ": {"count": 1, "lat": "33.3624385", "lon": "-111.745916582599"}, "Neptune, NJ": {"count": 1, "lat": "40.2239981", "lon": "-74.0478216"}, "Land O Lakes, FL": {"count": 1, "lat": "28.2188992", "lon": "-82.4575938"}, "Indianapolis, IN": {"count": 6, "lat": "39.7683331", "lon": "-86.1583501"}, "Southfield, MI": {"count": 3, "lat": "42.4733689", "lon": "-83.2218731"}, "Fairview Heights, IL": {"count": 1, "lat": "25.0205375", "lon": "-77.358790996939"}, "Escondido, CA": {"count": 1, "lat": "33.1216751", "lon": "-117.0814849"}, "Pittsburgh, PA": {"count": 1, "lat": "40.4416941", "lon": "-79.9900861"}, "Troy, MI": {"count": 1, "lat": "42.6055893", "lon": "-83.1499304"}, "Saline, MI": {"count": 1, "lat": "39.1256186", "lon": "-93.2300648"}, "Canton, OH": {"count": 1, "lat": "40.7989522", "lon": "-81.3784445"}, "Grand Blanc, MI": {"count": 1, "lat": "42.9275277", "lon": "-83.6299518"}, "Clarkston, MI": {"count": 1, "lat": "42.7086411", "lon": "-83.4396633"}, "Lombard, IL": {"count": 1, "lat": "41.8800296", "lon": "-88.0078435"}, "Philadelphia, PA": {"count": 2, "lat": "39.9523993", "lon": "-75.1635898"}, "Midland, MI": {"count": 1, "lat": "43.6155825", "lon": "-84.2472117"}, "Phoenix, AZ": {"count": 1, "lat": "33.4467681", "lon": "-112.0756724"}, "Lutz, FL": {"count": 1, "lat": "28.1301047", "lon": "-82.4591822980172"}, "Rochester Hills, MI": {"count": 1, "lat": "42.6583661", "lon": "-83.1499322"}, "Cincinnati, OH": {"count": 2, "lat": "39.1014537", "lon": "-84.5124602"}, "St. Paul, MN": {"count": 2, "lat": "44.9504037", "lon": "-93.1015025"}, "Duncan, SC": {"count": 1, "lat": "34.9378962", "lon": "-82.1451096"}, "Sandusky, OH": {"count": 1, "lat": "41.4489397", "lon": "-82.7079605"}, "Lincolnshire, IL": {"count": 2, "lat": "53.166667", "lon": "-0.25"}, "Cleveland, OH": {"count": 1, "lat": "41.5051613", "lon": "-81.6934446"}, "Metamora, MI": {"count": 1, "lat": "42.9414173", "lon": "-83.2891092"}, "Raleigh, NC": {"count": 1, "lat": "35.7804015", "lon": "-78.6390779"}, "Birmingham, MI": {"count": 1, "lat": "33.5206824", "lon": "-86.8024326"}, "Zephyrhills, FL": {"count": 1, "lat": "28.241311", "lon": "-82.1852348923161"}, "Niles, MI": {"count": 1, "lat": "41.8297694", "lon": "-86.2541768"}, "Casper, WY": {"count": 1, "lat": "42.866632", "lon": "-106.313081"}, "Neenah, WI": {"count": 1, "lat": "44.1858193", "lon": "-88.462609"}, "Rocky Mount, NC": {"count": 1, "lat": "35.9423833", "lon": "-77.7956948"}, "Lake Orion, MI": {"count": 1, "lat": "42.7844752", "lon": "-83.2396612"}, "Richmond, VA": {"count": 1, "lat": "37.5385087", "lon": "-77.4342799"}, "Eagleville, PA": {"count": 1, "lat": "41.0564538", "lon": "-77.5927705"}, "Tampa, FL": {"count": 1, "lat": "27.9477595", "lon": "-82.458444"}, "Lapeer, MI": {"count": 1, "lat": "43.0904764", "lon": "-83.2333705"}, "Los Angeles, CA": {"count": 1, "lat": "34.0543942", "lon": "-118.2439408"}, "Grand Rapids, MI": {"count": 1, "lat": "42.9632405", "lon": "-85.6678639"}, "Industry, PA": {"count": 1, "lat": "40.6445099", "lon": "-80.4161761"}, "Livonia, MI": {"count": 2, "lat": "42.36837", "lon": "-83.3527097"}, "Muskegon, MI": {"count": 1, "lat": "43.2341813", "lon": "-86.2483921"}, "Maumee, OH": {"count": 1, "lat": "41.5628294", "lon": "-83.6538244"}, "Saint John, IN": {"count": 1, "lat": "38.0792104", "lon": "-87.4500133"}, "Newbury Park, CA": {"count": 1, "lat": "34.184172", "lon": "-118.9106525"}, "Chicago, IL": {"count": 1, "lat": "41.8755546", "lon": "-87.6244212"}, "Owosso, MI": {"count": 1, "lat": "42.9978049", "lon": "-84.1766359"}, "Sparta, IL": {"count": 1, "lat": "38.1231053", "lon": "-89.7017658"}, "Mukwonago, WI": {"count": 1, "lat": "42.8666803", "lon": "-88.3334274"}, "Mentor, OH": {"count": 1, "lat": "41.6661573", "lon": "-81.339552"}}, "name": "Eastern Michigan", "license": "Data \u00a9 OpenStreetMap contributors, ODbL 1.0. http://www.openstreetmap.org/copyright"}