{"color": "#372286", "hometowns": {"Hazlet, NJ": {"count": 1, "lat": "40.4156635", "lon": "-74.1909769"}, "River Forest, IL": {"count": 1, "lat": "41.8978091", "lon": "-87.8139483"}, "Chino Hills, CA": {"count": 1, "lat": "33.9926803", "lon": "-117.760056"}, "Ponte Vedra, FL": {"count": 1, "lat": "30.2274645", "lon": "-81.3800824"}, "Concord Township, OH": {"count": 1, "lat": "39.0220092", "lon": "-84.0802113"}, "Long Branch, NJ": {"count": 1, "lat": "40.3042778", "lon": "-73.9923596"}, "Atlanta, GA": {"count": 1, "lat": "33.7490987", "lon": "-84.3901849"}, "Monrovia, CA": {"count": 1, "lat": "34.1483499", "lon": "-118.0014517"}, "Verona, NJ": {"count": 2, "lat": "40.829822", "lon": "-74.2401466"}, "Kirkwood, MO": {"count": 1, "lat": "38.5776995", "lon": "-90.418654740625"}, "Mansfield, TX": {"count": 1, "lat": "32.5631924", "lon": "-97.1416768"}, "Lake Zurich, IL": {"count": 1, "lat": "42.1969689", "lon": "-88.0934108"}, "Scituate, MA": {"count": 1, "lat": "42.1959348", "lon": "-70.725874"}, "Honolulu, HI": {"count": 1, "lat": "21.304547", "lon": "-157.8556764"}, "Pickerington, OH": {"count": 1, "lat": "39.8842304", "lon": "-82.7535049"}, "Lemont, IL": {"count": 1, "lat": "41.673642", "lon": "-88.0017261"}, "LAWRENCE, KS": {"count": 1, "lat": "38.9719384", "lon": "-95.2359496"}, "Hamden, OH": {"count": 1, "lat": "39.1597938", "lon": "-82.5268259"}, "Houston, TX": {"count": 3, "lat": "29.7589382", "lon": "-95.3676973"}, "Union City, CA": {"count": 1, "lat": "37.5963232", "lon": "-122.0816297"}, "Peru, IL": {"count": 1, "lat": "-10.1199999", "lon": "-76.2913223858673"}, "Lauderdale Lakes, FL": {"count": 1, "lat": "26.1681519", "lon": "-80.2047179854773"}, "Leawood, KS": {"count": 1, "lat": "38.966673", "lon": "-94.6169012"}, "Lawrenceburg, KY": {"count": 1, "lat": "38.0372967", "lon": "-84.8966171"}, "Romeoville, IL": {"count": 1, "lat": "41.6475306", "lon": "-88.0895061"}, "Bolingbrook, IL": {"count": 1, "lat": "41.7003302", "lon": "-88.0717708"}, "Lewis Center, OH": {"count": 1, "lat": "40.1983958", "lon": "-83.0101843"}, "Lakewood, OH": {"count": 1, "lat": "41.4819932", "lon": "-81.7981908"}, "Forney, TX": {"count": 1, "lat": "32.747893", "lon": "-96.4719289"}, "Barrington, IL": {"count": 1, "lat": "42.1539141", "lon": "-88.1361888"}, "Buffalo Grove, IL": {"count": 1, "lat": "42.1675825", "lon": "-87.9556401083333"}, "Englewood, NJ": {"count": 2, "lat": "40.8928771", "lon": "-73.9726381"}, "Naperville, IL": {"count": 1, "lat": "41.7729107", "lon": "-88.147867"}, "LaGrange Highlands, IL": {"count": 1, "lat": "27.507559", "lon": "-81.4460879"}, "Royersford, PA": {"count": 1, "lat": "40.1842688", "lon": "-75.5379639"}, "Allen, TX": {"count": 1, "lat": "33.1031744", "lon": "-96.6705503"}, "Memphis, TN": {"count": 1, "lat": "35.1490215", "lon": "-90.0516285"}, "Urbana, OH": {"count": 1, "lat": "40.1083912", "lon": "-83.7524298"}, "Cedar Hill, TX": {"count": 1, "lat": "32.5889112", "lon": "-96.9559308"}, "Morristown, NJ": {"count": 1, "lat": "40.7970209", "lon": "-74.481011"}, "Ashland, OH": {"count": 1, "lat": "40.7887367", "lon": "-82.2360391"}, "Plano, IL": {"count": 1, "lat": "33.0136764", "lon": "-96.6925096"}, "West Bloomfield, MI": {"count": 1, "lat": "44.2208134", "lon": "-88.9717809"}, "University Heights, OH": {"count": 1, "lat": "41.4978306", "lon": "-81.5373456"}, "Bloomfield Hills, MI": {"count": 2, "lat": "42.583645", "lon": "-83.2454883"}, "Plano, TX": {"count": 1, "lat": "33.0136764", "lon": "-96.6925096"}, "Indianapolis, IN": {"count": 1, "lat": "39.7683331", "lon": "-86.1583501"}, "Ballston Lake, NY": {"count": 1, "lat": "42.9117428", "lon": "-73.8681782"}, "Lorain, OH": {"count": 1, "lat": "41.452819", "lon": "-82.1823746"}, "San Diego, CA": {"count": 1, "lat": "32.7174209", "lon": "-117.1627714"}, "Toledo, OH": {"count": 1, "lat": "41.6786754", "lon": "-83.5127283"}, "Dallas, TX": {"count": 1, "lat": "32.7762719", "lon": "-96.7968558"}, "Pittsburgh, PA": {"count": 1, "lat": "40.4416941", "lon": "-79.9900861"}, "Erie, PA": {"count": 1, "lat": "42.1290657", "lon": "-80.0852421"}, "Long Beach, CA": {"count": 1, "lat": "33.7774658", "lon": "-118.1884871"}, "Carol Stream, IL": {"count": 1, "lat": "41.9125286", "lon": "-88.1347927"}, "Plainfield, IL": {"count": 2, "lat": "41.623191", "lon": "-88.2284324789042"}, "Jacksonville, IL": {"count": 1, "lat": "30.3321838", "lon": "-81.655651"}, "The Plains, OH": {"count": 1, "lat": "39.3700911", "lon": "-82.1323674"}, "Avon, IN": {"count": 1, "lat": "39.7628227", "lon": "-86.3997168"}, "Baton Rouge, LA": {"count": 1, "lat": "30.4507462", "lon": "-91.154551"}, "Lombard, IL": {"count": 1, "lat": "41.8800296", "lon": "-88.0078435"}, "Midland, MI": {"count": 1, "lat": "43.6155825", "lon": "-84.2472117"}, "Crown Point, IN": {"count": 1, "lat": "41.4169806", "lon": "-87.3653136"}, "Benicia, CA": {"count": 1, "lat": "38.049365", "lon": "-122.1585777"}, "Gaithersburg, MD": {"count": 1, "lat": "39.1434406", "lon": "-77.2013705"}, "Pewaukee, WI": {"count": 1, "lat": "43.0805651", "lon": "-88.2612045"}, "Cincinnati, OH": {"count": 3, "lat": "39.1014537", "lon": "-84.5124602"}, "Sudbury, MA": {"count": 1, "lat": "42.3834278", "lon": "-71.4161725"}, "Buford, GA": {"count": 1, "lat": "34.1206564", "lon": "-84.0043513"}, "Coppell, TX": {"count": 1, "lat": "32.958352", "lon": "-96.9881829964861"}, "Chagrin Falls, OH": {"count": 1, "lat": "41.4361644", "lon": "-81.3865012"}, "Oak Park, IL": {"count": 2, "lat": "41.8850317", "lon": "-87.7845025"}, "USA": {"count": 1, "lat": "39.7837304", "lon": "-100.4458824"}, "Cordele, GA": {"count": 1, "lat": "31.9635074", "lon": "-83.7823938"}, "Centerville, OH": {"count": 1, "lat": "39.6283928", "lon": "-84.1593818"}, "Trout Valley, IL": {"count": 1, "lat": "42.1980798", "lon": "-88.2534159"}, "Baltimore, MD": {"count": 1, "lat": "39.2908608", "lon": "-76.6108073"}, "Park Ridge, IL": {"count": 1, "lat": "42.0111412", "lon": "-87.8406192"}, "Kenosha, WI": {"count": 1, "lat": "42.5846773", "lon": "-87.8212263"}, "The Woodlands, TX": {"count": 1, "lat": "30.1734194", "lon": "-95.504686"}, "Wheaton, IL": {"count": 3, "lat": "41.8646959", "lon": "-88.1101709"}, "Rockford, IL": {"count": 1, "lat": "42.2713945", "lon": "-89.093966"}, "Malvern, PA": {"count": 1, "lat": "40.036202", "lon": "-75.5138959"}, "Grand Rapids, MI": {"count": 1, "lat": "42.9632405", "lon": "-85.6678639"}, "Miami, FL": {"count": 1, "lat": "25.7742658", "lon": "-80.1936589"}, "Lancaster, PA": {"count": 1, "lat": "40.03813", "lon": "-76.3056686"}, "Owings Mills, MD": {"count": 1, "lat": "39.4010753", "lon": "-76.796299"}, "Wamego, KS": {"count": 1, "lat": "39.2019412", "lon": "-96.3049976"}, "Bourbonnais, IL": {"count": 1, "lat": "41.1639309", "lon": "-87.8839693"}, "Avon Lake, OH": {"count": 1, "lat": "41.5053178", "lon": "-82.0282001"}, "Chicago, IL": {"count": 1, "lat": "41.8755546", "lon": "-87.6244212"}, "Brentwood, CA": {"count": 1, "lat": "37.9317766", "lon": "-121.6960266"}, "Santa Monica, CA": {"count": 1, "lat": "34.0195598", "lon": "-118.4869739"}, "Peninsula, OH": {"count": 1, "lat": "41.2411668", "lon": "-81.5526176"}, "Orlando, FL": {"count": 1, "lat": "28.5421175", "lon": "-81.3790462"}}, "name": "Northwestern", "license": "Data \u00a9 OpenStreetMap contributors, ODbL 1.0. http://www.openstreetmap.org/copyright"}