{"color": "#003263", "hometowns": {"Matthews, NC": {"count": 1, "lat": "35.1168131", "lon": "-80.7236804"}, "Mcdonald, PA": {"count": 1, "lat": "40.3709025", "lon": "-80.2347814"}, "Detroit, MI": {"count": 1, "lat": "42.3486635", "lon": "-83.0567375"}, "Duquesne, PA": {"count": 1, "lat": "40.3814581", "lon": "-79.8597708"}, "Madison, WI": {"count": 1, "lat": "43.074761", "lon": "-89.3837612"}, "Seattle, WA": {"count": 1, "lat": "47.6038321", "lon": "-122.3300624"}, "Washington, PA": {"count": 1, "lat": "40.1943798", "lon": "-80.2541251"}, "Greensburg, PA": {"count": 1, "lat": "40.3014581", "lon": "-79.5389289"}, "Canton, OH": {"count": 1, "lat": "40.7989522", "lon": "-81.3784445"}, "Loveland, OH": {"count": 1, "lat": "39.2689562", "lon": "-84.2638406"}, "Stephens City, VA": {"count": 1, "lat": "39.0834398", "lon": "-78.2180567"}, "Dexter, MI": {"count": 1, "lat": "42.3383697", "lon": "-83.8885553"}, "Cocoa, FL": {"count": 1, "lat": "28.3821505", "lon": "-80.7757979975217"}, "Wilmington, DE": {"count": 2, "lat": "39.7459468", "lon": "-75.546589"}, "Rockville, MD": {"count": 1, "lat": "39.0840054", "lon": "-77.1527573"}, "Youngstown, OH": {"count": 1, "lat": "41.0997803", "lon": "-80.6495194"}, "Silver Spring, MD": {"count": 1, "lat": "38.9906657", "lon": "-77.026088"}, "Coraopolis, PA": {"count": 1, "lat": "40.5184013", "lon": "-80.1667247"}, "Turtle Creek, PA": {"count": 1, "lat": "40.405926", "lon": "-79.8250534"}, "Chelsea, MI": {"count": 1, "lat": "42.3917638", "lon": "-71.0328284"}, "Milwaukee, WI": {"count": 1, "lat": "43.0349931", "lon": "-87.922497"}, "Kaneohe, HI": {"count": 1, "lat": "21.4055", "lon": "-157.796071507204"}, "Richmond, VA": {"count": 1, "lat": "37.5385087", "lon": "-77.4342799"}, "Niagara Falls, NY": {"count": 1, "lat": "43.1030928", "lon": "-79.0302618"}, "Rankin, PA": {"count": 1, "lat": "40.412569", "lon": "-79.8792161"}, "Washington, NJ": {"count": 1, "lat": "40.7584326", "lon": "-74.9793378"}, "Mashpee, MA": {"count": 1, "lat": "41.6484421", "lon": "-70.4811383"}, "Greenville, VA": {"count": 1, "lat": "38.7178955", "lon": "-77.6624913"}, "Dallas, TX": {"count": 1, "lat": "32.7762719", "lon": "-96.7968558"}, "Tampa, FL": {"count": 1, "lat": "27.9477595", "lon": "-82.458444"}, "Carlisle, PA": {"count": 1, "lat": "40.201824", "lon": "-77.1893888"}, "Oconomowoc, WI": {"count": 1, "lat": "43.1116731", "lon": "-88.4992659"}, "Kissimmee, FL": {"count": 1, "lat": "28.2920249", "lon": "-81.4078013"}, "Pittsburgh, PA": {"count": 12, "lat": "40.4416941", "lon": "-79.9900861"}, "Erie, PA": {"count": 1, "lat": "42.1290657", "lon": "-80.0852421"}, "Rochester, NY": {"count": 1, "lat": "43.1854754", "lon": "-77.6106860508176"}, "Murrysville, PA": {"count": 1, "lat": "40.4284015", "lon": "-79.697545"}, "Bethel Park, PA": {"count": 1, "lat": "40.3275697", "lon": "-80.0394977"}, "Somerville, MA": {"count": 1, "lat": "42.3875968", "lon": "-71.0994968"}, "Sylvania, OH": {"count": 1, "lat": "41.7189392", "lon": "-83.7129935"}, "Voorhees, NJ": {"count": 1, "lat": "40.4812157", "lon": "-74.4832088"}, "Newburgh, NY": {"count": 1, "lat": "41.5034271", "lon": "-74.0104179"}, "Plantation, FL": {"count": 1, "lat": "26.1265258", "lon": "-80.257861037651"}, "Dyer, IN": {"count": 1, "lat": "41.4942021", "lon": "-87.5217068"}, "Mansfield, TX": {"count": 1, "lat": "32.5631924", "lon": "-97.1416768"}, "Apollo, PA": {"count": 1, "lat": "40.5814546", "lon": "-79.5664333"}, "Maria Stein, OH": {"count": 1, "lat": "40.4078249", "lon": "-84.4932862"}, "Elizabeth, PA": {"count": 1, "lat": "40.2692367", "lon": "-79.8897706"}, "Reading, OH": {"count": 1, "lat": "39.2236694", "lon": "-84.4421641"}, "Miami, FL": {"count": 1, "lat": "25.7742658", "lon": "-80.1936589"}, "Wexford, PA": {"count": 2, "lat": "40.6264561", "lon": "-80.055891"}, "Wilkes-barre, PA": {"count": 1, "lat": "41.2464824", "lon": "-75.8817316"}, "Harrisburg, PA": {"count": 3, "lat": "40.2663107", "lon": "-76.8861122"}, "Trotwood, OH": {"count": 1, "lat": "39.7972788", "lon": "-84.3113334"}, "Columbus, OH": {"count": 3, "lat": "39.9622601", "lon": "-83.0007065"}, "Philadelphia, PA": {"count": 4, "lat": "39.9523993", "lon": "-75.1635898"}, "Cleveland, TN": {"count": 1, "lat": "35.1595182", "lon": "-84.8766115"}, "O Fallon, IL": {"count": 1, "lat": "39.3910354", "lon": "-118.7020485"}, "New Castle, PA": {"count": 1, "lat": "41.0036719", "lon": "-80.3470091"}, "Alexandria, VA": {"count": 1, "lat": "38.8051095", "lon": "-77.0470229"}, "Maple Glen, PA": {"count": 1, "lat": "40.178412", "lon": "-75.1778195384532"}, "Forest Hills, PA": {"count": 1, "lat": "40.4197911", "lon": "-79.8500487"}, "Canonsburg, PA": {"count": 1, "lat": "40.2625702", "lon": "-80.1872797"}, "Paterson, NJ": {"count": 1, "lat": "40.9167654", "lon": "-74.171811"}, "Clairton, PA": {"count": 2, "lat": "40.292292", "lon": "-79.881715"}, "Cranford, NJ": {"count": 1, "lat": "40.6584358", "lon": "-74.2995923"}, "Mckees Rocks, PA": {"count": 2, "lat": "40.4656244", "lon": "-80.0656106"}, "Collingdale, PA": {"count": 1, "lat": "39.9117794", "lon": "-75.2771292"}, "Fairborn, OH": {"count": 1, "lat": "39.8067455", "lon": "-84.0102331768371"}, "Chicago, IL": {"count": 1, "lat": "41.8755546", "lon": "-87.6244212"}, "Belle Vernon, PA": {"count": 1, "lat": "40.1250725", "lon": "-79.8664356"}, "Aliquippa, PA": {"count": 1, "lat": "40.6102386", "lon": "-80.267726"}, "Lake Dallas, TX": {"count": 1, "lat": "33.1192875", "lon": "-97.0255641"}, "Jacksonville, FL": {"count": 1, "lat": "30.3321838", "lon": "-81.655651"}, "Buffalo, NY": {"count": 1, "lat": "42.8864468", "lon": "-78.8783689"}, "Wilkinsburg, PA": {"count": 1, "lat": "40.4417355", "lon": "-79.8819942"}, "Monroeville, PA": {"count": 1, "lat": "40.4211798", "lon": "-79.7881025"}, "New London, WI": {"count": 1, "lat": "44.3927581", "lon": "-88.7398255"}, "Coatesville, PA": {"count": 2, "lat": "39.9831616", "lon": "-75.8238355"}, "Dayton, OH": {"count": 1, "lat": "39.7589478", "lon": "-84.1916069"}, "Chambersburg, PA": {"count": 1, "lat": "39.9405903", "lon": "-77.6598624"}, "Waynesburg, PA": {"count": 1, "lat": "39.8964641", "lon": "-80.1792299"}, "Toledo, OH": {"count": 1, "lat": "41.6786754", "lon": "-83.5127283"}, "Cleveland, OH": {"count": 1, "lat": "41.5051613", "lon": "-81.6934446"}, "New Kensington, PA": {"count": 1, "lat": "40.5697893", "lon": "-79.7647705"}}, "name": "Pittsburgh", "license": "Data \u00a9 OpenStreetMap contributors, ODbL 1.0. http://www.openstreetmap.org/copyright"}