{"color": "#c00", "hometowns": {"Manchester, MO": {"count": 1, "lat": "38.5852465", "lon": "-90.514782036191"}, "Springfield, IL": {"count": 3, "lat": "39.7989763", "lon": "-89.6443687"}, "USA": {"count": 9, "lat": "39.7837304", "lon": "-100.4458824"}, "Saint Clair, MO": {"count": 1, "lat": "38.3453291", "lon": "-90.9809734"}, "Champaign, IL": {"count": 1, "lat": "40.1164205", "lon": "-88.2433828"}, "Boca Raton, FL": {"count": 1, "lat": "26.3586885", "lon": "-80.0830983"}, "Largo, FL": {"count": 1, "lat": "27.9094665", "lon": "-82.7873243"}, "Springfield, MO": {"count": 1, "lat": "37.2153307", "lon": "-93.298252"}, "Poplar Bluff, MO": {"count": 4, "lat": "36.7569994", "lon": "-90.392888"}, "Humble, TX": {"count": 1, "lat": "29.9988312", "lon": "-95.2621552"}, "Warrenton, MO": {"count": 1, "lat": "38.811436", "lon": "-91.1415374"}, "East Saint Louis, IL": {"count": 1, "lat": "38.6244952", "lon": "-90.1509428"}, "Jacksonville, FL": {"count": 2, "lat": "30.3321838", "lon": "-81.6556509"}, "Alton, IL": {"count": 2, "lat": "38.8906038", "lon": "-90.1842763"}, "Owasso, OK": {"count": 1, "lat": "36.2661536", "lon": "-95.8549455"}, "Spring, TX": {"count": 1, "lat": "30.0798826", "lon": "-95.4172548"}, "Willingboro, NJ": {"count": 1, "lat": "40.0278894", "lon": "-74.8690541"}, "Dexter, MO": {"count": 1, "lat": "36.7958866", "lon": "-89.9578687"}, "Cape Girardeau, MO": {"count": 1, "lat": "37.3058839", "lon": "-89.5181475"}, "Maumelle, AR": {"count": 1, "lat": "34.8667565", "lon": "-92.4043218"}, "Florissant, MO": {"count": 1, "lat": "38.789217", "lon": "-90.3226139"}, "St. Charles, MO": {"count": 1, "lat": "38.783194", "lon": "-90.482368"}, "Tampa, FL": {"count": 2, "lat": "27.9477595", "lon": "-82.4584439"}, "Lincoln, NE": {"count": 1, "lat": "40.8000554", "lon": "-96.6674004"}, "Loxahatchee, FL": {"count": 1, "lat": "26.6836769", "lon": "-80.2797699"}, "Surprise, AZ": {"count": 1, "lat": "33.6292271", "lon": "-112.3680188"}, "Kennett, MO": {"count": 1, "lat": "36.2361763", "lon": "-90.0556493"}, "Saint Charles, MO": {"count": 2, "lat": "38.783194", "lon": "-90.482368"}, "Kansas City, MO": {"count": 2, "lat": "39.0844687", "lon": "-94.5630297"}, "Webster Groves, MO": {"count": 1, "lat": "38.586494", "lon": "-90.3557750772251"}, "Bonne Terre, MO": {"count": 1, "lat": "37.9231069", "lon": "-90.5554038"}, "Kirkwood, MO": {"count": 2, "lat": "38.5776995", "lon": "-90.418654790625"}, "Troy, IL": {"count": 1, "lat": "38.7292147", "lon": "-89.883154"}, "Wichita, KS": {"count": 1, "lat": "37.6922361", "lon": "-97.3375447"}, "Biloxi, MS": {"count": 1, "lat": "30.374673", "lon": "-88.8459432348286"}, "Owensville, MO": {"count": 1, "lat": "38.3456023", "lon": "-91.5015486"}, "Southaven, MS": {"count": 1, "lat": "34.9889818", "lon": "-90.0125912"}, "Nashville, TN": {"count": 1, "lat": "36.1622296", "lon": "-86.774353"}, "Miami, FL": {"count": 1, "lat": "25.7742658", "lon": "-80.1936588"}, "Birmingham, AL": {"count": 2, "lat": "33.5206824", "lon": "-86.8024325"}, "Caruthersville, MO": {"count": 1, "lat": "36.1931245", "lon": "-89.6556352"}, "Olathe, KS": {"count": 1, "lat": "38.8843867", "lon": "-94.8161126"}, "South Elgin, IL": {"count": 1, "lat": "41.9941938", "lon": "-88.2922995"}, "Memphis, TN": {"count": 5, "lat": "35.1490215", "lon": "-90.0516284"}, "Newburgh, IN": {"count": 1, "lat": "37.9456824", "lon": "-87.404657"}, "Troy, TN": {"count": 1, "lat": "36.338677", "lon": "-89.1639566"}, "Clearwater, FL": {"count": 1, "lat": "27.9658533", "lon": "-82.8001025"}, "Louisville, KY": {"count": 3, "lat": "38.2542376", "lon": "-85.7594069"}, "Godfrey, IL": {"count": 1, "lat": "38.9556031", "lon": "-90.1867764"}, "Farmington, MO": {"count": 3, "lat": "36.7304288", "lon": "-108.208919"}, "Potosi, MO": {"count": 1, "lat": "37.936438", "lon": "-90.7879085"}, "Jackson, MO": {"count": 2, "lat": "37.3822732", "lon": "-89.6662063"}, "Monterey Park, CA": {"count": 1, "lat": "34.0512156", "lon": "-118.1292289"}, "Chicago, IL": {"count": 1, "lat": "41.8755546", "lon": "-87.6244211"}, "Shawnee, KS": {"count": 1, "lat": "39.0416718", "lon": "-94.7202375"}, "Marion, IL": {"count": 1, "lat": "37.7306054", "lon": "-88.9331255"}, "Inglewood, CA": {"count": 1, "lat": "33.9616801", "lon": "-118.353131"}, "Collierville, TN": {"count": 1, "lat": "35.042036", "lon": "-89.6645265"}, "Hillsboro, MO": {"count": 2, "lat": "38.2322766", "lon": "-90.5629033"}, "Carlinville, IL": {"count": 1, "lat": "39.2797699", "lon": "-89.8817661"}, "Royal Palm Beach, FL": {"count": 2, "lat": "26.7017553", "lon": "-80.223384128483"}, "Mccomb, MS": {"count": 1, "lat": "31.2437872", "lon": "-90.4531535"}, "Scott City, MO": {"count": 1, "lat": "37.2167175", "lon": "-89.5245335"}, "Arlington, TX": {"count": 1, "lat": "32.7355816", "lon": "-97.1071185"}, "Ithaca, MI": {"count": 1, "lat": "43.2916975", "lon": "-84.6075003"}, "Owensboro, KY": {"count": 1, "lat": "37.7742152", "lon": "-87.1133303"}}, "name": "Southeast Missouri State", "license": "Data \u00a9 OpenStreetMap contributors, ODbL 1.0. http://www.openstreetmap.org/copyright"}