{"color": "#00488F", "hometowns": {"Charlotte, NC": {"count": 2, "lat": "35.2270869", "lon": "-80.8431268", "license": "Data \u00a9 OpenStreetMap contributors, ODbL 1.0. http://www.openstreetmap.org/copyright"}, "Garfield Heights, OH": {"count": 1, "lat": "41.4169974", "lon": "-81.6059581", "license": "Data \u00a9 OpenStreetMap contributors, ODbL 1.0. http://www.openstreetmap.org/copyright"}, "Detroit, MI": {"count": 2, "lat": "42.3486635", "lon": "-83.0567375", "license": "Data \u00a9 OpenStreetMap contributors, ODbL 1.0. http://www.openstreetmap.org/copyright"}, "Peachtree City, GA": {"count": 1, "lat": "33.3967829", "lon": "-84.5957629", "license": "Data \u00a9 OpenStreetMap contributors, ODbL 1.0. http://www.openstreetmap.org/copyright"}, "Pomfret, MD": {"count": 1, "lat": "38.5773417", "lon": "-77.030531", "license": "Data \u00a9 OpenStreetMap contributors, ODbL 1.0. http://www.openstreetmap.org/copyright"}, "Anna, OH": {"count": 1, "lat": "40.3944932", "lon": "-84.1727231", "license": "Data \u00a9 OpenStreetMap contributors, ODbL 1.0. http://www.openstreetmap.org/copyright"}, "Tulsa, OK": {"count": 1, "lat": "36.1556805", "lon": "-95.9929113", "license": "Data \u00a9 OpenStreetMap contributors, ODbL 1.0. http://www.openstreetmap.org/copyright"}, "London, OH": {"count": 1, "lat": "39.8864493", "lon": "-83.448253", "license": "Data \u00a9 OpenStreetMap contributors, ODbL 1.0. http://www.openstreetmap.org/copyright"}, "Monroe, MI": {"count": 2, "lat": "33.8884929", "lon": "-88.4747009", "license": "Data \u00a9 OpenStreetMap contributors, ODbL 1.0. http://www.openstreetmap.org/copyright"}, "Morenci, MI": {"count": 1, "lat": "41.7195109", "lon": "-84.2173964", "license": "Data \u00a9 OpenStreetMap contributors, ODbL 1.0. http://www.openstreetmap.org/copyright"}, "Beavercreek, OH": {"count": 1, "lat": "39.7092262", "lon": "-84.0632685", "license": "Data \u00a9 OpenStreetMap contributors, ODbL 1.0. http://www.openstreetmap.org/copyright"}, "Columbia Station, OH": {"count": 1, "lat": "41.3131066", "lon": "-81.9468057", "license": "Data \u00a9 OpenStreetMap contributors, ODbL 1.0. http://www.openstreetmap.org/copyright"}, "Upper Marlboro, MD": {"count": 1, "lat": "38.8162654", "lon": "-76.7518462", "license": "Data \u00a9 OpenStreetMap contributors, ODbL 1.0. http://www.openstreetmap.org/copyright"}, "Youngstown, OH": {"count": 1, "lat": "41.0997803", "lon": "-80.6495194", "license": "Data \u00a9 OpenStreetMap contributors, ODbL 1.0. http://www.openstreetmap.org/copyright"}, "Richmond, TX": {"count": 1, "lat": "29.5821811", "lon": "-95.7607832", "license": "Data \u00a9 OpenStreetMap contributors, ODbL 1.0. http://www.openstreetmap.org/copyright"}, "Gary, IN": {"count": 1, "lat": "41.6021292", "lon": "-87.3371372", "license": "Data \u00a9 OpenStreetMap contributors, ODbL 1.0. http://www.openstreetmap.org/copyright"}, "Downers Grove, IL": {"count": 1, "lat": "41.7946074", "lon": "-88.0068999", "license": "Data \u00a9 OpenStreetMap contributors, ODbL 1.0. http://www.openstreetmap.org/copyright"}, "Baltimore, MD": {"count": 3, "lat": "39.2908608", "lon": "-76.6108073", "license": "Data \u00a9 OpenStreetMap contributors, ODbL 1.0. http://www.openstreetmap.org/copyright"}, "Port Huron, MI": {"count": 1, "lat": "42.9815877", "lon": "-82.440466", "license": "Data \u00a9 OpenStreetMap contributors, ODbL 1.0. http://www.openstreetmap.org/copyright"}, "Ashville, OH": {"count": 1, "lat": "39.7156186", "lon": "-82.9529584", "license": "Data \u00a9 OpenStreetMap contributors, ODbL 1.0. http://www.openstreetmap.org/copyright"}, "Centerville, OH": {"count": 1, "lat": "39.6283928", "lon": "-84.1593818", "license": "Data \u00a9 OpenStreetMap contributors, ODbL 1.0. http://www.openstreetmap.org/copyright"}, "Northwood, OH": {"count": 1, "lat": "41.607272", "lon": "-83.4688204", "license": "Data \u00a9 OpenStreetMap contributors, ODbL 1.0. http://www.openstreetmap.org/copyright"}, "Pittsburgh, PA": {"count": 9, "lat": "40.4416941", "lon": "-79.9900861", "license": "Data \u00a9 OpenStreetMap contributors, ODbL 1.0. http://www.openstreetmap.org/copyright"}, "Pickerington, OH": {"count": 1, "lat": "39.8842304", "lon": "-82.7535049", "license": "Data \u00a9 OpenStreetMap contributors, ODbL 1.0. http://www.openstreetmap.org/copyright"}, "Burlington, NJ": {"count": 1, "lat": "39.9325409", "lon": "-74.7226665", "license": "Data \u00a9 OpenStreetMap contributors, ODbL 1.0. http://www.openstreetmap.org/copyright"}, "Toledo, OH": {"count": 8, "lat": "41.6786754", "lon": "-83.5127283", "license": "Data \u00a9 OpenStreetMap contributors, ODbL 1.0. http://www.openstreetmap.org/copyright"}, "Grafton, OH": {"count": 1, "lat": "41.2725522", "lon": "-82.0545892", "license": "Data \u00a9 OpenStreetMap contributors, ODbL 1.0. http://www.openstreetmap.org/copyright"}, "Tampa, FL": {"count": 4, "lat": "27.9477595", "lon": "-82.458444", "license": "Data \u00a9 OpenStreetMap contributors, ODbL 1.0. http://www.openstreetmap.org/copyright"}, "Galloway, OH": {"count": 1, "lat": "39.9139207", "lon": "-83.1633336", "license": "Data \u00a9 OpenStreetMap contributors, ODbL 1.0. http://www.openstreetmap.org/copyright"}, "Hubbard, OH": {"count": 1, "lat": "41.1564463", "lon": "-80.569239", "license": "Data \u00a9 OpenStreetMap contributors, ODbL 1.0. http://www.openstreetmap.org/copyright"}, "Willoughby, OH": {"count": 3, "lat": "41.6397696", "lon": "-81.4065011", "license": "Data \u00a9 OpenStreetMap contributors, ODbL 1.0. http://www.openstreetmap.org/copyright"}, "Schaumburg, IL": {"count": 1, "lat": "42.0333608", "lon": "-88.083406", "license": "Data \u00a9 OpenStreetMap contributors, ODbL 1.0. http://www.openstreetmap.org/copyright"}, "Washington, DC": {"count": 1, "lat": "38.8949549", "lon": "-77.0366456", "license": "Data \u00a9 OpenStreetMap contributors, ODbL 1.0. http://www.openstreetmap.org/copyright"}, "Powell, OH": {"count": 1, "lat": "40.1578403", "lon": "-83.0751869", "license": "Data \u00a9 OpenStreetMap contributors, ODbL 1.0. http://www.openstreetmap.org/copyright"}, "Barrington, IL": {"count": 1, "lat": "42.1539141", "lon": "-88.1361888", "license": "Data \u00a9 OpenStreetMap contributors, ODbL 1.0. http://www.openstreetmap.org/copyright"}, "Massillon, OH": {"count": 1, "lat": "40.7967244", "lon": "-81.5215093", "license": "Data \u00a9 OpenStreetMap contributors, ODbL 1.0. http://www.openstreetmap.org/copyright"}, "Lake Wales, FL": {"count": 1, "lat": "27.9014133", "lon": "-81.5859099", "license": "Data \u00a9 OpenStreetMap contributors, ODbL 1.0. http://www.openstreetmap.org/copyright"}, "Chagrin Falls, OH": {"count": 1, "lat": "41.4361644", "lon": "-81.3865012", "license": "Data \u00a9 OpenStreetMap contributors, ODbL 1.0. http://www.openstreetmap.org/copyright"}, "Waynesboro, VA": {"count": 1, "lat": "38.065698", "lon": "-78.9055212867161", "license": "Data \u00a9 OpenStreetMap contributors, ODbL 1.0. http://www.openstreetmap.org/copyright"}, "Sterling, VA": {"count": 1, "lat": "39.0016194", "lon": "-77.4032011", "license": "Data \u00a9 OpenStreetMap contributors, ODbL 1.0. http://www.openstreetmap.org/copyright"}, "Huron, OH": {"count": 1, "lat": "41.1305303", "lon": "-82.591828", "license": "Data \u00a9 OpenStreetMap contributors, ODbL 1.0. http://www.openstreetmap.org/copyright"}, "Mason, OH": {"count": 2, "lat": "39.3600586", "lon": "-84.309939", "license": "Data \u00a9 OpenStreetMap contributors, ODbL 1.0. http://www.openstreetmap.org/copyright"}, "Delphos, OH": {"count": 1, "lat": "40.8433831", "lon": "-84.341618", "license": "Data \u00a9 OpenStreetMap contributors, ODbL 1.0. http://www.openstreetmap.org/copyright"}, "Grand Blanc, MI": {"count": 1, "lat": "42.9275277", "lon": "-83.6299518", "license": "Data \u00a9 OpenStreetMap contributors, ODbL 1.0. http://www.openstreetmap.org/copyright"}, "Miami, FL": {"count": 1, "lat": "25.7742658", "lon": "-80.1936589", "license": "Data \u00a9 OpenStreetMap contributors, ODbL 1.0. http://www.openstreetmap.org/copyright"}, "Coppell, TX": {"count": 1, "lat": "32.958352", "lon": "-96.9881829964861", "license": "Data \u00a9 OpenStreetMap contributors, ODbL 1.0. http://www.openstreetmap.org/copyright"}, "Rossford, OH": {"count": 1, "lat": "41.6097726", "lon": "-83.5643782", "license": "Data \u00a9 OpenStreetMap contributors, ODbL 1.0. http://www.openstreetmap.org/copyright"}, "Hilton Head Island, SC": {"count": 1, "lat": "32.216316", "lon": "-80.752608", "license": "Data \u00a9 OpenStreetMap contributors, ODbL 1.0. http://www.openstreetmap.org/copyright"}, "Algonquin, IL": {"count": 1, "lat": "42.1655801", "lon": "-88.2942493", "license": "Data \u00a9 OpenStreetMap contributors, ODbL 1.0. http://www.openstreetmap.org/copyright"}, "Mansfield, OH": {"count": 1, "lat": "40.75839", "lon": "-82.5154471", "license": "Data \u00a9 OpenStreetMap contributors, ODbL 1.0. http://www.openstreetmap.org/copyright"}, "Copley, OH": {"count": 1, "lat": "41.0989439", "lon": "-81.6445685", "license": "Data \u00a9 OpenStreetMap contributors, ODbL 1.0. http://www.openstreetmap.org/copyright"}, "Hilliard, OH": {"count": 2, "lat": "40.033814", "lon": "-83.1596108", "license": "Data \u00a9 OpenStreetMap contributors, ODbL 1.0. http://www.openstreetmap.org/copyright"}, "Akron, OH": {"count": 1, "lat": "41.0830643", "lon": "-81.5184854", "license": "Data \u00a9 OpenStreetMap contributors, ODbL 1.0. http://www.openstreetmap.org/copyright"}, "Aurora, OH": {"count": 1, "lat": "41.3175549", "lon": "-81.3453858", "license": "Data \u00a9 OpenStreetMap contributors, ODbL 1.0. http://www.openstreetmap.org/copyright"}, "Sumter, SC": {"count": 1, "lat": "33.9204354", "lon": "-80.3414693", "license": "Data \u00a9 OpenStreetMap contributors, ODbL 1.0. http://www.openstreetmap.org/copyright"}, "Clyde, OH": {"count": 1, "lat": "41.3042201", "lon": "-82.975192", "license": "Data \u00a9 OpenStreetMap contributors, ODbL 1.0. http://www.openstreetmap.org/copyright"}, "Ruskin, FL": {"count": 1, "lat": "27.7208575", "lon": "-82.4331528", "license": "Data \u00a9 OpenStreetMap contributors, ODbL 1.0. http://www.openstreetmap.org/copyright"}, "Dayton, OH": {"count": 1, "lat": "39.7589478", "lon": "-84.1916069", "license": "Data \u00a9 OpenStreetMap contributors, ODbL 1.0. http://www.openstreetmap.org/copyright"}, "Sagamore Hills, OH": {"count": 1, "lat": "41.3365056", "lon": "-81.5617791", "license": "Data \u00a9 OpenStreetMap contributors, ODbL 1.0. http://www.openstreetmap.org/copyright"}, "Columbus, OH": {"count": 2, "lat": "39.9622601", "lon": "-83.0007065", "license": "Data \u00a9 OpenStreetMap contributors, ODbL 1.0. http://www.openstreetmap.org/copyright"}, "Sunbury, OH": {"count": 1, "lat": "40.2425623", "lon": "-82.8590673", "license": "Data \u00a9 OpenStreetMap contributors, ODbL 1.0. http://www.openstreetmap.org/copyright"}, "South Rockwood, MI": {"count": 1, "lat": "42.0639323", "lon": "-83.2610406", "license": "Data \u00a9 OpenStreetMap contributors, ODbL 1.0. http://www.openstreetmap.org/copyright"}, "Hudson, OH": {"count": 2, "lat": "41.240056", "lon": "-81.440667", "license": "Data \u00a9 OpenStreetMap contributors, ODbL 1.0. http://www.openstreetmap.org/copyright"}, "Grand Rapids, MI": {"count": 1, "lat": "42.9632405", "lon": "-85.6678639", "license": "Data \u00a9 OpenStreetMap contributors, ODbL 1.0. http://www.openstreetmap.org/copyright"}, "Aliquippa, PA": {"count": 1, "lat": "40.6102386", "lon": "-80.267726", "license": "Data \u00a9 OpenStreetMap contributors, ODbL 1.0. http://www.openstreetmap.org/copyright"}, "Cincinnati, OH": {"count": 5, "lat": "39.1014537", "lon": "-84.5124602", "license": "Data \u00a9 OpenStreetMap contributors, ODbL 1.0. http://www.openstreetmap.org/copyright"}, "North Olmsted, OH": {"count": 1, "lat": "41.4156025", "lon": "-81.9234725", "license": "Data \u00a9 OpenStreetMap contributors, ODbL 1.0. http://www.openstreetmap.org/copyright"}, "Frankfort, KY": {"count": 1, "lat": "38.2009055", "lon": "-84.8732836", "license": "Data \u00a9 OpenStreetMap contributors, ODbL 1.0. http://www.openstreetmap.org/copyright"}, "Portage, MI": {"count": 1, "lat": "42.2011538", "lon": "-85.5800022", "license": "Data \u00a9 OpenStreetMap contributors, ODbL 1.0. http://www.openstreetmap.org/copyright"}, "Cleveland, OH": {"count": 2, "lat": "41.5051613", "lon": "-81.6934446", "license": "Data \u00a9 OpenStreetMap contributors, ODbL 1.0. http://www.openstreetmap.org/copyright"}, "Leesburg, VA": {"count": 1, "lat": "39.1026092", "lon": "-77.5590106451901", "license": "Data \u00a9 OpenStreetMap contributors, ODbL 1.0. http://www.openstreetmap.org/copyright"}, "Elyria, OH": {"count": 2, "lat": "41.3683798", "lon": "-82.1076486", "license": "Data \u00a9 OpenStreetMap contributors, ODbL 1.0. http://www.openstreetmap.org/copyright"}, "Marrero, LA": {"count": 1, "lat": "29.8993723", "lon": "-90.1003506", "license": "Data \u00a9 OpenStreetMap contributors, ODbL 1.0. http://www.openstreetmap.org/copyright"}, "Sandusky, OH": {"count": 1, "lat": "41.4489397", "lon": "-82.7079605", "license": "Data \u00a9 OpenStreetMap contributors, ODbL 1.0. http://www.openstreetmap.org/copyright"}, "Marion, IN": {"count": 1, "lat": "40.5583739", "lon": "-85.6591442", "license": "Data \u00a9 OpenStreetMap contributors, ODbL 1.0. http://www.openstreetmap.org/copyright"}}, "name": "Toledo"}